Workbook

Sheet Inputs
A1: INFOSYS LTD (NSE: INFY) - DCF VALUATION MODEL
A3: MARKET DATA
A4: Current Share Price (₹) | B4: 1183 | C4: NSE close, 10-Aug-2026 Yahoo Finance
A5: Shares Outstanding (Cr) | B5: 405 | C5: ≈ Equity Capital ₹2,024 Cr ÷ ₹5 face value (FY26); matches ~4.05bn shares reported by data providers
A6: Valuation / Base Year | B6: FY2026A (year ended 31-Mar-2026)
A8: SCENARIO TOGGLE
A9: Scenario (1 = Bull, 2 = Base, 3 = Bear) | B9: 2
A10: Growth adjustment applied to every forecast year (pp) | B10: =CHOOSE(B9,2,0,-2)/100 -> 0
A12: REVENUE GROWTH % - 5 YEAR FORECAST (FY27–FY31)
A13: Fiscal Year | B13: FY27E | C13: FY28E | D13: FY29E | E13: FY30E | F13: FY31E
A14: Base-case Revenue Growth % | B14: 0.1 | C14: 0.09 | D14: 0.08 | E14: 0.07 | F14: 0.06
A15: Tapers from 10% in FY27E toward ~6% by FY31E, reflecting normalization from FY26A growth of 9.6% toward recent mid-single-digit Indian IT-services industry growth. Historical 3Y/5Y sales CAGR is ~7%/~12%.
A16: Scenario-Adjusted Revenue Growth % | B16: =B14+$B$10 -> 0.1 | C16: =C14+$B$10 -> 0.09 | D16: =D14+$B$10 -> 0.08 | E16: =E14+$B$10 -> 0.07 | F16: =F14+$B$10 -> 0.06
A18: MARGIN & FCF DRIVERS
A19: Fiscal Year | B19: FY27E | C19: FY28E | D19: FY29E | E19: FY30E | F19: FY31E
A20: EBITDA Margin % | B20: 0.238 | C20: 0.24 | D20: 0.242 | E20: 0.244 | F20: 0.245
A21: FY26A: 23.7%; gradual expansion reflecting efficiency improvements.
A22: Tax Rate % | B22: 0.26 | C22: FY26A effective tax rate: 26.0%; held constant.
A23: D&A % of Revenue | B23: 0.028 | C23: ~FY26A: 4,902 / 178,650 = 2.7%
A24: Capex % of Revenue | B24: 0.015 | C24: FY26A Capex (derived) / Revenue = 2,727/178,650 ≈ 1.5%
A25: Net Working Capital (Days of Revenue) | B25: 33 | C25: FY26A: 33 days; held constant
A27: WACC BUILD (CAPM)
A28: Risk-free Rate, Rf (10Y India G-Sec) | B28: 0.0676 | C28: Source: CCIL , As of: 10-Aug-2026
A29: Equity Risk Premium, ERP (India) | B29: 0.073 | C29: Source: Damodaran (NYU Stern), Country Risk Premium dataset , July 2026 semiannual update
A30: Beta | B30: ='Beta Calc'!B3 -> 0.9054368
A31: Cost of Equity | B31: =B28+B30*B29 -> 0.13369689
A32: Pre-tax Cost of Debt | B32: =Historicals!G32 -> 0.047807849
A33: Post-tax Cost of Debt | B33: =B32*(1-B22) -> 0.035377808
A34: Market Value of Equity (₹ Cr) | B34: =B4*B5 -> 479115
A35: Market Value of Debt (₹ Cr, FY26A borrowings) | B35: =Historicals!G16 -> 9176
A36: Equity Weight | B36: =B34/(B34+B35) -> 0.98120793
A37: Debt Weight | B37: =B35/(B34+B35) -> 0.018792073
A38: WACC | B38: =B31*B36+B33*B37 -> 0.13184927
A40: TERMINAL VALUE
A41: Terminal Growth Rate, g (Gordon Growth) | B41: 0.04 | C41: Kept ≤ long-run India nominal GDP growth ,maintains >8 pt spread to WACC per Gordon Growth convention.

Sheet Historicals
A1: INFOSYS LTD - 5 YEAR HISTORICALS (FY22A - FY26A) + RATIO ANALYSIS
A3: INCOME STATEMENT (₹ Crore, Consolidated IFRS)
A4: Particulars | B4: FY21A | C4: FY22A | D4: FY23A | E4: FY24A | F4: FY25A | G4: FY26A
A5: Revenue | B5: 100472 | C5: 121641 | D5: 146767 | E5: 153670 | F5: 162990 | G5: 178650
A6: Revenue Growth % YoY | C6: =C5/B5-1 -> 0.21069552 | D6: =D5/C5-1 -> 0.20655864 | E6: =E5/D5-1 -> 0.047033734 | F6: =F5/E5-1 -> 0.060649444 | G6: =G5/F5-1 -> 0.096079514
A7: EBITDA | B7: 27889 | C7: 31491 | D7: 35130 | E7: 36425 | F7: 39236 | G7: 42280
A8: EBITDA Margin % | B8: =B7/B5 -> 0.27757982 | C8: =C7/C5 -> 0.25888475 | D8: =D7/D5 -> 0.23935898 | E8: =E7/E5 -> 0.2370339 | F8: =F7/F5 -> 0.24072642 | G8: =G7/G5 -> 0.23666387
A9: Depreciation & Amortisation | B9: 3267 | C9: 3476 | D9: 4225 | E9: 4678 | F9: 4812 | G9: 4902
A10: EBIT | B10: =B7-B9 -> 24622 | C10: =C7-C9 -> 28015 | D10: =D7-D9 -> 30905 | E10: =E7-E9 -> 31747 | F10: =F7-F9 -> 34424 | G10: =G7-G9 -> 37378
A11: Net Profit | B11: 19423 | C11: 22146 | D11: 24108 | E11: 26248 | F11: 26750 | G11: 29474
A12: Effective Tax Rate % | B12: 0.27 | C12: 0.26 | D12: 0.28 | E12: 0.27 | F12: 0.29 | G12: 0.26
A14: BALANCE SHEET & CAPITAL STRUCTURE (₹ Crore)
A15: Particulars | B15: FY21A | C15: FY22A | D15: FY23A | E15: FY24A | F15: FY25A | G15: FY26A
A16: Total Borrowings (Debt) | B16: 5325 | C16: 5474 | D16: 8299 | E16: 8359 | F16: 8227 | G16: 9176
A17: Cash & Cash Equivalents | C17: 17472 | D17: 12173 | E17: 14786 | F17: 24455 | G17: 22201
A18: Net Debt | C18: =C16-C17 -> -11998 | D18: =D16-D17 -> -3874 | E18: =E16-E17 -> -6427 | F18: =F16-F17 -> -16228 | G18: =G16-G17 -> -13025
A20: Working Capital Days | B20: 36 | C20: 28 | D20: 31 | E20: 54 | F20: 39 | G20: 33
A21: Net Working Capital (₹ Cr) | B21: =B5*B20/365 -> 9909.5671 | C21: =C5*C20/365 -> 9331.3644 | D21: =D5*D20/365 -> 12465.142 | E21: =E5*E20/365 -> 22734.74 | F21: =F5*F20/365 -> 17415.37 | G21: =G5*G20/365 -> 16151.918
A23: CASH FLOW & COST OF DEBT (₹ Crore)
A24: Particulars | B24: FY21A | C24: FY22A | D24: FY23A | E24: FY24A | F24: FY25A | G24: FY26A
A25: Cash from Operating Activity | B25: 23224 | C25: 23885 | D25: 22467 | E25: 25210 | F25: 35694 | G25: 33986
A26: Free Cash Flow | B26: 21117 | C26: 21724 | D26: 19888 | E26: 23009 | F26: 33457 | G26: 31259
A27: Capex | B27: =B25-B26 -> 2107 | C27: =C25-C26 -> 2161 | D27: =D25-D26 -> 2579 | E27: =E25-E26 -> 2201 | F27: =F25-F26 -> 2237 | G27: =G25-G26 -> 2727
A28: Capex % of Revenue | B28: =B27/B5 -> 0.020971017 | C28: =C27/C5 -> 0.017765392 | D28: =D27/D5 -> 0.01757207 | E28: =E27/E5 -> 0.0143229 | F28: =F27/F5 -> 0.013724768 | G28: =G27/G5 -> 0.015264484
A30: Interest | G30: 416
A31: Average Debt | G31: =(F16+G16)/2 -> 8701.5
A32: Pre-tax Cost of Debt | G32: =G30/G31 -> 0.047807849

Sheet Beta Calc
A1: BETA REGRESSION - 5Y Weekly Returns, INFY vs NIFTY 50 (SLOPE)
A3: Beta (5Y weekly, SLOPE) | B3: =SLOPE(D7:D266,E7:E266) -> 0.9054368
A5: Date | B5: INFY Close (₹) | C5: NIFTY50 Close | D5: INFY Weekly Return | E5: NIFTY Weekly Return
A6: 46243 | B6: 1182 | C6: 24583.8
A7: 46236 | B7: 1175.1 | C7: 24570.65 | D7: =B7/B6-1 -> -0.0058375635 | E7: =C7/C6-1 -> -0.0005349051
A8: 46229 | B8: 1130.1 | C8: 24383.6 | D8: =B8/B7-1 -> -0.038294613 | E8: =C8/C7-1 -> -0.0076127412
A9: 46222 | B9: 1040.9 | C9: 23767.45 | D9: =B9/B8-1 -> -0.078931068 | E9: =C9/C8-1 -> -0.025269033
A10: 46215 | B10: 1096.5 | C10: 24334.3 | D10: =B10/B9-1 -> 0.053415314 | E10: =C10/C9-1 -> 0.023849845
A11: 46208 | B11: 1068 | C11: 24206.9 | D11: =B11/B10-1 -> -0.025991792 | E11: =C11/C10-1 -> -0.0052354085
A12: 46201 | B12: 1047.2 | C12: 24270.85 | D12: =B12/B11-1 -> -0.019475655 | E12: =C12/C11-1 -> 0.0026418087
A13: 46194 | B13: 1041.2 | C13: 24056 | D13: =B13/B12-1 -> -0.0057295646 | E13: =C13/C12-1 -> -0.0088521828
A14: 46187 | B14: 1051.4 | C14: 24013.1 | D14: =B14/B13-1 -> 0.0097963888 | E14: =C14/C13-1 -> -0.0017833389
A15: 46180 | B15: 1116.4 | C15: 23622.9 | D15: =B15/B14-1 -> 0.061822332 | E15: =C15/C14-1 -> -0.016249464
A16: 46173 | B16: 1197.5 | C16: 23366.7 | D16: =B16/B15-1 -> 0.072644214 | E16: =C16/C15-1 -> -0.010845408
A17: 46166 | B17: 1160.9 | C17: 23547.75 | D17: =B17/B16-1 -> -0.030563674 | E17: =C17/C16-1 -> 0.0077482058
A18: 46159 | B18: 1174.5 | C18: 23719.3 | D18: =B18/B17-1 -> 0.011715049 | E18: =C18/C17-1 -> 0.0072851971
... A266: 44423 | B266: 1723.24 | C266: 16450.5 | D266: =B266/B265-1 -> 0.014135898 | E266: =C266/C265-1 -> -0.01524675
A267: Source:Investing.com -5Y weekly regression (SLOPE), INFY vs Nifty 50, 09-Aug-2021 to 09-Aug-2026

Sheet Forecast
A1: 5-YEAR DRIVER BASED FORECAST (FY27E- FY31E)
A3: FORECAST P&L & FREE CASH FLOW TO FIRM (₹ Crore)
A4: Particulars | B4: FY27E | C4: FY28E | D4: FY29E | E4: FY30E | F4: FY31E
A5: Revenue | B5: =Historicals!G5*(1+Inputs!B16) -> 196515 | C5: =B5*(1+Inputs!C16) -> 214201.35 | D5: =C5*(1+Inputs!D16) -> 231337.46 | E5: =D5*(1+Inputs!E16) -> 247531.08 | F5: =E5*(1+Inputs!F16) -> 262382.94
A6: Revenue Growth % | B6: =Inputs!B16 -> 0.1 | C6: =Inputs!C16 -> 0.09 | D6: =Inputs!D16 -> 0.08 | E6: =Inputs!E16 -> 0.07 | F6: =Inputs!F16 -> 0.06
A7: EBITDA | B7: =B5*Inputs!B20 -> 46770.57 | C7: =C5*Inputs!C20 -> 51408.324 | D7: =D5*Inputs!D20 -> 55983.665 | E7: =E5*Inputs!E20 -> 60397.584 | F7: =F5*Inputs!F20 -> 64283.821
A8: EBITDA Margin % | B8: =Inputs!B20 -> 0.238 | C8: =Inputs!C20 -> 0.24 | D8: =Inputs!D20 -> 0.242 | E8: =Inputs!E20 -> 0.244 | F8: =Inputs!F20 -> 0.245
A9: Depreciation & Amortisation | B9: =B5*Inputs!$B$23 -> 5502.42 | C9: =C5*Inputs!$B$23 -> 5997.6378 | D9: =D5*Inputs!$B$23 -> 6477.4488 | E9: =E5*Inputs!$B$23 -> 6930.8702 | F9: =F5*Inputs!$B$23 -> 7346.7225
A10: EBIT | B10: =B7-B9 -> 41268.15 | C10: =C7-C9 -> 45410.686 | D10: =D7-D9 -> 49506.216 | E10: =E7-E9 -> 53466.713 | F10: =F7-F9 -> 56937.099
A11: Less: Tax on EBIT | B11: =B10*Inputs!$B$22 -> 10729.719 | C11: =C10*Inputs!$B$22 -> 11806.778 | D11: =D10*Inputs!$B$22 -> 12871.616 | E11: =E10*Inputs!$B$22 -> 13901.345 | F11: =F10*Inputs!$B$22 -> 14803.646
A12: NOPAT | B12: =B10-B11 -> 30538.431 | C12: =C10-C11 -> 33603.908 | D12: =D10-D11 -> 36634.6 | E12: =E10-E11 -> 39565.368 | F12: =F10-F11 -> 42133.453
A13: (+) Add back D&A | B13: =B9 -> 5502.42 | C13: =C9 -> 5997.6378 | D13: =D9 -> 6477.4488 | E13: =E9 -> 6930.8702 | F13: =F9 -> 7346.7225
A14: (−) Capex | B14: =B5*Inputs!$B$24 -> 2947.725 | C14: =C5*Inputs!$B$24 -> 3213.0203 | D14: =D5*Inputs!$B$24 -> 3470.0619 | E14: =E5*Inputs!$B$24 -> 3712.9662 | F14: =F5*Inputs!$B$24 -> 3935.7442
A15: Net Working Capital (₹ Cr) | B15: =B5*Inputs!$B$25/365 -> 17767.11 | C15: =C5*Inputs!$B$25/365 -> 19366.149 | D15: =D5*Inputs!$B$25/365 -> 20915.441 | E15: =E5*Inputs!$B$25/365 -> 22379.522 | F15: =F5*Inputs!$B$25/365 -> 23722.294
A16: (−) Increase in Net Working Capital | B16: =B15-Historicals!G21 -> 1615.1918 | C16: =C15-B15 -> 1599.0399 | D16: =D15-C15 -> 1549.292 | E16: =E15-D15 -> 1464.0809 | F16: =F15-E15 -> 1342.7713
A17: FREE CASH FLOW TO FIRM (FCFF) | B17: =B12+B13-B14-B16 -> 31477.934 | C17: =C12+C13-C14-C16 -> 34789.485 | D17: =D12+D13-D14-D16 -> 38092.695 | E17: =E12+E13-E14-E16 -> 41319.191 | F17: =F12+F13-F14-F16 -> 44201.66

Sheet DCF
A1: DISCOUNTED CASH FLOW - ENTERPRISE VALUE TO PER-SHARE VALUE
A3: STEP 1 - DISCOUNT EXPLICIT FCFF (FY27E-FY31E)
A4: Particulars | B4: FY27E | C4: FY28E | D4: FY29E | E4: FY30E | F4: FY31E
A5: Forecast Year (n) | B5: 1 | C5: 2 | D5: 3 | E5: 4 | F5: 5
A6: FCFF | B6: =Forecast!B17 -> 31477.934 | C6: =Forecast!C17 -> 34789.485 | D6: =Forecast!D17 -> 38092.695 | E6: =Forecast!E17 -> 41319.191 | F6: =Forecast!F17 -> 44201.66
A7: Discount Factor | B7: =1/(1+Inputs!$B$38)^B5 -> 0.88350987 | C7: =1/(1+Inputs!$B$38)^C5 -> 0.78058969 | D7: =1/(1+Inputs!$B$38)^D5 -> 0.6896587 | E7: =1/(1+Inputs!$B$38)^E5 -> 0.60932027 | F7: =1/(1+Inputs!$B$38)^F5 -> 0.53834047
A8: PV of FCFF | B8: =B6*B7 -> 27811.066 | C8: =C6*C7 -> 27156.314 | D8: =D6*D7 -> 26270.958 | E8: =E6*E7 -> 25176.621 | F8: =F6*F7 -> 23795.543
A10: STEP 2 - TERMINAL VALUE (GORDON GROWTH)
A11: Sum of PV of FCFF (FY27E-FY31E) | B11: =SUM(B8:F8) -> 130210.5
A12: Terminal Value | B12: =F6*(1+Inputs!B41)/(Inputs!B38-Inputs!B41) -> 500490.95
A13: PV of Terminal Value | B13: =B12/(1+Inputs!B38)^5 -> 269434.53
A15: STEP 3 - ENTERPRISE VALUE | EQUITY VALUE | PER-SHARE VALUE
A16: Enterprise Value | B16: =B11+B13 -> 399645.03
A17: TV as % of Enterprise Value | B17: =B13/B16 -> 0.67418461
A18: Less: Net Debt (FY26A, from Historicals) | B18: =Historicals!G18 -> -13025
A19: Equity Value | B19: =B16-B18 -> 412670.03
A20: ÷ Shares Outstanding (Cr) | B20: =Inputs!B5 -> 405
A21: INTRINSIC VALUE PER SHARE | B21: =B19/B20 -> 1018.9384
A22: Current Market Price | B22: =Inputs!B4 -> 1183
A23: Implied Upside / (Downside) | B23: =B21/B22-1 -> -0.13868271
A25: STEP 4 - TWO WAY SENSITIVITY: VALUE PER SHARE (₹) - WACC (rows) × Terminal Growth g (columns)
A26: WACC \ g | B26: =Inputs!$B$41+(-0.01) -> 0.03 | C26: =Inputs!$B$41+(-0.005) -> 0.035 | D26: =Inputs!$B$41+(0) -> 0.04 | E26: =Inputs!$B$41+(0.005) -> 0.045 | F26: =Inputs!$B$41+(0.01) -> 0.05
A27: =Inputs!$B$38+(-0.01) -> 0.12184927 | B27: {=(SUMPRODUCT(Forecast!$B$17:$F$17,1/(1+$A27)^{1,2,3,4,5})+(Forecast!$F$17*(1+B$26)/($A27-B$26))/(1+$A27)^5-B18)/B20} -> 1050.9103 | C27: {=(SUMPRODUCT(Forecast!$B$17:$F$17,1/(1+$A27)^{1,2,3,4,5})+(Forecast!$F$17*(1+C$26)/($A27-C$26))/(1+$A27)^5-B18)/B20} -> 1094.0993 | D27: {=(SUMPRODUCT(Forecast!$B$17:$F$17,1/(1+$A27)^{1,2,3,4,5})+(Forecast!$F$17*(1+D$26)/($A27-D$26))/(1+$A27)^5-B18)/B20} -> 1142.565 | E27: {=(SUMPRODUCT(Forecast!B17:F17,1/(1+$A27)^{1,2,3,4,5})+(Forecast!$F$17*(1+E$26)/($A27-E$26))/(1+$A27)^5-B18)/B20} -> 1197.3373 | F27: {=(SUMPRODUCT(Forecast!$B$17:$F$17,1/(1+$A27)^{1,2,3,4,5})+(Forecast!$F$17*(1+F$26)/($A27-F$26))/(1+$A27)^5-B18)/B20} -> 1259.7329
A28: =Inputs!$B$38+(-0.005) -> 0.12684927 | B28: {=(SUMPRODUCT(Forecast!$B$17:$F$17,1/(1+$A28)^{1,2,3,4,5})+(Forecast!$F$17*(1+B$26)/($A28-B$26))/(1+$A28)^5-B18)/B20} -> 996.70682 | C28: {=(SUMPRODUCT(Forecast!$B$17:$F$17,1/(1+$A28)^{1,2,3,4,5})+(Forecast!$F$17*(1+C$26)/($A28-C$26))/(1+$A28)^5-B18)/B20} -> 1034.7536 | D28: {=(SUMPRODUCT(Forecast!$B$17:$F$17,1/(1+$A28)^{1,2,3,4,5})+(Forecast!$F$17*(1+D$26)/($A28-D$26))/(1+$A28)^5-B18)/B20} -> 1077.1812 | E28: {=(SUMPRODUCT(Forecast!$B$17:$F$17,1/(1+$A28)^{1,2,3,4,5})+(Forecast!$F$17*(1+E$26)/($A28-E$26))/(1+$A28)^5-B18)/B20} -> 1124.7924 | F28: {=(SUMPRODUCT(Forecast!$B$17:$F$17,1/(1+$A28)^{1,2,3,4,5})+(Forecast!$F$17*(1+F$26)/($A28-F$26))/(1+$A28)^5-B18)/B20} -> 1178.5991
A29: =Inputs!$B$38+(0) -> 0.13184927 | B29: {=(SUMPRODUCT(Forecast!$B$17:$F$17,1/(1+$A29)^{1,2,3,4,5})+(Forecast!$F$17*(1+B$26)/($A29-B$26))/(1+$A29)^5-B18)/B20} -> 947.85047 | C29: {=(SUMPRODUCT(Forecast!$B$17:$F$17,1/(1+$A29)^{1,2,3,4,5})+(Forecast!$F$17*(1+C$26)/($A29-C$26))/(1+$A29)^5-B18)/B20} -> 981.5594 | D29: {=(SUMPRODUCT(Forecast!$B$17:$F$17,1/(1+$A29)^{1,2,3,4,5})+(Forecast!$F$17*(1+D$26)/($A29-D$26))/(1+$A29)^5-B18)/B20} -> 1018.9384 | E29: {=(SUMPRODUCT(Forecast!$B$17:$F$17,1/(1+$A29)^{1,2,3,4,5})+(Forecast!$F$17*(1+E$26)/($A29-E$26))/(1+$A29)^5-B18)/B20} -> 1060.6212 | F29: {=(SUMPRODUCT(Forecast!$B$17:$F$17,1/(1+$A29)^{1,2,3,4,5})+(Forecast!$F$17*(1+F$26)/($A29-F$26))/(1+$A29)^5-B18)/B20} -> 1107.3967
A30: =Inputs!$B$38+(0.005) -> 0.13684927 | B30: {=(SUMPRODUCT(Forecast!$B$17:$F$17,1/(1+$A30)^{1,2,3,4,5})+(Forecast!$F$17*(1+B$26)/($A30-B$26))/(1+$A30)^5-B18)/B20} -> 903.59004 | C30: {=(SUMPRODUCT(Forecast!$B$17:$F$17,1/(1+$A30)^{1,2,3,4,5})+(Forecast!$F$17*(1+C$26)/($A30-C$26))/(1+$A30)^5-B18)/B20} -> 933.61017 | D30: {=(SUMPRODUCT(Forecast!$B$17:$F$17,1/(1+$A30)^{1,2,3,4,5})+(Forecast!$F$17*(1+D$26)/($A30-D$26))/(1+$A30)^5-B18)/B20} -> 966.72997 | E30: {=(SUMPRODUCT(Forecast!$B$17:$F$17,1/(1+$A30)^{1,2,3,4,5})+(Forecast!$F$17*(1+E$26)/($A30-E$26))/(1+$A30)^5-B18)/B20} -> 1003.4557 | F30: {=(SUMPRODUCT(Forecast!$B$17:$F$17,1/(1+$A30)^{1,2,3,4,5})+(Forecast!$F$17*(1+F$26)/($A30-F$26))/(1+$A30)^5-B18)/B20} -> 1044.41
A31: =Inputs!$B$38+(0.01) -> 0.14184927 | B31: {=(SUMPRODUCT(Forecast!$B$17:$F$17,1/(1+$A31)^{1,2,3,4,5})+(Forecast!$F$17*(1+B$26)/($A31-B$26))/(1+$A31)^5-B18)/B20} -> 863.30868 | C31: {=(SUMPRODUCT(Forecast!$B$17:$F$17,1/(1+$A31)^{1,2,3,4,5})+(Forecast!$F$17*(1+C$26)/($A31-C$26))/(1+$A31)^5-B18)/B20} -> 890.16916 | D31: {=(SUMPRODUCT(Forecast!$B$17:$F$17,1/(1+$A31)^{1,2,3,4,5})+(Forecast!$F$17*(1+D$26)/($A31-D$26))/(1+$A31)^5-B18)/B20} -> 919.66692 | E31: {=(SUMPRODUCT(Forecast!$B$17:$F$17,1/(1+$A31)^{1,2,3,4,5})+(Forecast!$F$17*(1+E$26)/($A31-E$26))/(1+$A31)^5-B18)/B20} -> 952.21042 | F31: {=(SUMPRODUCT(Forecast!$B$17:$F$17,1/(1+$A31)^{1,2,3,4,5})+(Forecast!$F$17*(1+F$26)/($A31-F$26))/(1+$A31)^5-B18)/B20} -> 988.29705

Sheet Comps
A1: RELATIVE VALUATION - PEER COMPARABLE COMPANIES
A3: PEER SET - MARKET DATA (as of 08-10 August 2026)
A4: Company | B4: Mkt Cap (₹Cr) | C4: TTM Revenue (₹Cr) | D4: TTM Net Profit (₹Cr) | E4: P/E (x) | F4: EV/EBITDA (x)
A5: Tata Consultancy Services (TCS) | B5: 887408.33 | C5: 275859 | D5: 53690.47 | E5: =B5/D5 -> 16.528228 | F5: 11.3
A6: HCL Technologies (HCLTECH) | B6: 368135.81 | C6: 134374 | D6: 18130.33 | E6: =B6/D6 -> 20.30497 | F6: 12.06
A7: Wipro (WIPRO) | B7: 185737.13 | C7: 94968 | D7: 13219 | E7: =B7/D7 -> 14.05077 | F7: 8.88
A8: Tech Mahindra (TECHM) | B8: 160243.87 | C8: 59176.1 | D8: 5320.57 | E8: =B8/D8 -> 30.117801 | F8: 16.49
A11: PEER MEDIAN MULTIPLES
A12: Median Peer P/E | B12: =MEDIAN(E5:E8) -> 18.416599
A13: Median Peer EV/EBITDA | B13: =MEDIAN(F5:F8) -> 11.68
A15: APPLY PEER MULTIPLES TO INFOSYS (FY27E)
A16: Infosys FY27E NOPAT (₹Cr) | B16: =Forecast!B12 -> 30538.431
A17: Infosys FY27E EBITDA (₹Cr) | B17: =Forecast!B7 -> 46770.57
A18: Shares Outstanding (Cr) | B18: =Inputs!$B$5 -> 405
A19: Net Debt (FY26A, ₹Cr) | B19: =Historicals!G18 -> -13025
A21: Implied Value/Share - P/E method | B21: =B12*(B16/B18) -> 1388.6766
A22: Implied Value/Share - EV/EBITDA method | B22: =(B13*B17-B19)/B18 -> 1381.0006

Sheet Output
A1: INFOSYS LTD - VALUATION OUTPUT SUMMARY
A3: Intrinsic Value / Share | B3: Current Market Price | C3: Implied Upside / (Downside) | D3: WACC | E3: TV % of EV
A4: =DCF!B21 -> 1018.9384 | B4: =DCF!B22 -> 1183 | C4: =DCF!B23 -> -0.13868271 | D4: =Inputs!B38 -> 0.13184927 | E4: =DCF!B17 -> 0.67418461
A6: VALUATION FOOTBALL FIELD - VALUE PER SHARE (₹) BY METHOD
A8: Method | B8: Low | C8: High | D8: Point Estimate | F8: Base (helper) | G8: Spread (helper)
A9: DCF (Sensitivity Range) | B9: =MIN(DCF!B27:F31) -> 863.30868 | C9: =MAX(DCF!B27:F31) -> 1259.7329 | D9: =DCF!B21 -> 1018.9384 | F9: =B9 -> 863.30868 | G9: =C9-B9 -> 396.42418
A10: P/E Comps (±5% of point estimate) | B10: =Comps!B21*0.95 -> 1319.2428 | C10: =Comps!B21*1.05 -> 1458.1105 | D10: =Comps!B21 -> 1388.6766 | F10: =B10 -> 1319.2428 | G10: =C10-B10 -> 138.86766
A11: EV/EBITDA Comps (±5%) | B11: =Comps!B22*0.95 -> 1311.9506 | C11: =Comps!B22*1.05 -> 1450.0507 | D11: =Comps!B22 -> 1381.0006 | F11: =B11 -> 1311.9506 | G11: =C11-B11 -> 138.10006
A12: Current Market Price | B12: =Inputs!$B$4 -> 1183 | C12: =Inputs!$B$4 -> 1183 | D12: =Inputs!$B$4 -> 1183 | F12: =B12 -> 1183 | G12: =C12-B12 -> 0
